README.md
setup.cfg
setup.py
rediscache_decorator/CacheDecorator.py
rediscache_decorator/__init__.py
rediscache_decorator.egg-info/PKG-INFO
rediscache_decorator.egg-info/SOURCES.txt
rediscache_decorator.egg-info/dependency_links.txt
rediscache_decorator.egg-info/requires.txt
rediscache_decorator.egg-info/top_level.txt