Metadata-Version: 2.1
Name: rediscache-decorator
Version: 1.0
Summary: Using redis as external rediscache_decorator with one line of code
Home-page: https://github.com/arthur-b-renaud
Author: Arthur RENAUD
Author-email: arthur@coalition.ai
License: MIT
Platform: UNKNOWN
Classifier: Programming Language :: Python :: 3
Classifier: License :: OSI Approved :: MIT License
Classifier: Operating System :: OS Independent
